odoo10_addon_hr_employee_seniority-10.0.1.0.2.99.dev12-py2.7-nspkg.pth
odoo/addons/hr_employee_seniority/README.rst
odoo/addons/hr_employee_seniority/__init__.py
odoo/addons/hr_employee_seniority/__manifest__.py
odoo/addons/hr_employee_seniority/i18n/ar.po
odoo/addons/hr_employee_seniority/i18n/cs_CZ.po
odoo/addons/hr_employee_seniority/i18n/de.po
odoo/addons/hr_employee_seniority/i18n/es.po
odoo/addons/hr_employee_seniority/i18n/fi.po
odoo/addons/hr_employee_seniority/i18n/fr.po
odoo/addons/hr_employee_seniority/i18n/hr.po
odoo/addons/hr_employee_seniority/i18n/hr_HR.po
odoo/addons/hr_employee_seniority/i18n/hr_employee_seniority.pot
odoo/addons/hr_employee_seniority/i18n/it.po
odoo/addons/hr_employee_seniority/i18n/lt.po
odoo/addons/hr_employee_seniority/i18n/nl_NL.po
odoo/addons/hr_employee_seniority/i18n/pt_BR.po
odoo/addons/hr_employee_seniority/i18n/ro.po
odoo/addons/hr_employee_seniority/i18n/sl.po
odoo/addons/hr_employee_seniority/models/__init__.py
odoo/addons/hr_employee_seniority/models/hr_employee.py
odoo/addons/hr_employee_seniority/static/description/icon.png
odoo/addons/hr_employee_seniority/tests/__init__.py
odoo/addons/hr_employee_seniority/tests/test_employee_seniority.py
odoo/addons/hr_employee_seniority/views/employee_views.xml
odoo10_addon_hr_employee_seniority-10.0.1.0.2.99.dev12.dist-info/METADATA
odoo10_addon_hr_employee_seniority-10.0.1.0.2.99.dev12.dist-info/RECORD
odoo10_addon_hr_employee_seniority-10.0.1.0.2.99.dev12.dist-info/WHEEL
odoo10_addon_hr_employee_seniority-10.0.1.0.2.99.dev12.dist-info/namespace_packages.txt
odoo10_addon_hr_employee_seniority-10.0.1.0.2.99.dev12.dist-info/top_level.txt
