Metadata-Version: 2.1
Name: odoo10-addon-hr-employee-seniority
Version: 10.0.1.0.2.99.dev12
Summary: Keep Track of Length of Employment
Home-page: http://miketelahun.wordpress.com
Author: Michael Telahun Makonnen <mmakonnen@gmail.com>, Camptocamp SA, Odoo Community Association (OCA)
Author-email: support@odoo-community.org
License: AGPL-3
Platform: UNKNOWN
Classifier: Programming Language :: Python
Classifier: Framework :: Odoo
Classifier: License :: OSI Approved :: GNU Affero General Public License v3
Requires-Python: ~=2.7
Requires-Dist: odoo (<10.1dev,>=10.0)
Requires-Dist: python-dateutil
